dsf_scoring_sdk/__init__.py
dsf_scoring_sdk/client.py
dsf_scoring_sdk/exceptions.py
dsf_scoring_sdk-1.0.11.dist-info/METADATA
dsf_scoring_sdk-1.0.11.dist-info/WHEEL
dsf_scoring_sdk-1.0.11.dist-info/top_level.txt
dsf_scoring_sdk-1.0.11.dist-info/RECORD
