Metadata-Version: 2.4
Name: dsf-scoring-sdk
Version: 1.0.11
Summary: SDK oficial en Python para la API de DSF Scoring
Home-page: https://github.com/jaimeajl/dsf-scoring-sdk
Author: Jaime Alexander Jimenez
Author-email: Jaime Alexander JImenez Lozano <contacto@dsfuptech.cloud>
License: Proprietary
Project-URL: Homepage, https://github.com/jaimeajl/dsf-scoring-sdk
Project-URL: Bug Tracker, https://github.com/jaimeajl/dsf-scoring-sdk/issues
Classifier: Programming Language :: Python :: 3
Classifier: License :: Other/Proprietary License
Classifier: Operating System :: OS Independent
Classifier: Topic :: Software Development :: Libraries :: Python Modules
Requires-Python: >=3.8
Requires-Dist: requests
Dynamic: author
Dynamic: home-page
Dynamic: requires-python
